[{"CONSTRAINT_CATALOG":"PSYCHOLOGY_TEST_1","CONSTRAINT_SCHEMA":"dbo","CONSTRAINT_NAME":"CK_T_MISSION_START_DATE","CHECK_CLAUSE":"([start_date]<[end_date])"},{"CONSTRAINT_CATALOG":"PSYCHOLOGY_TEST_1","CONSTRAINT_SCHEMA":"dbo","CONSTRAINT_NAME":"check_sex","CHECK_CLAUSE":"([sex]='f' OR [sex]='m')"},{"CONSTRAINT_CATALOG":"PSYCHOLOGY_TEST_1","CONSTRAINT_SCHEMA":"dbo","CONSTRAINT_NAME":"CK_T_TESTING_LANGUAGE","CHECK_CLAUSE":"([lang_num]=(3) OR [lang_num]=(2) OR [lang_num]=(1))"},{"CONSTRAINT_CATALOG":"PSYCHOLOGY_TEST_1","CONSTRAINT_SCHEMA":"dbo","CONSTRAINT_NAME":"CK_T_TEST_STEP","CHECK_CLAUSE":"([actual_mark]='n' OR [actual_mark]='y')"}]